ffp-0.2.0.dist-info/RECORD
ffp-0.2.0.dist-info/WHEEL
ffp-0.2.0.dist-info/top_level.txt
ffp-0.2.0.dist-info/METADATA
ffp-0.2.0.dist-info/LICENSE.md
ffp/embeddings.py
ffp/io.py
ffp/norms.py
ffp/__init__.py
ffp/metadata.py
ffp/vocab/vocab.py
ffp/vocab/cutoff.py
ffp/vocab/subword.py
ffp/vocab/__init__.py
ffp/vocab/simple_vocab.py
ffp/subwords/hash_indexers.pyx
ffp/subwords/ngrams.pyx
ffp/subwords/ngrams.c
ffp/subwords/explicit_indexer.cpython-36m-x86_64-linux-gnu.so
ffp/subwords/hash_indexers.cpython-36m-x86_64-linux-gnu.so
ffp/subwords/__init__.py
ffp/subwords/explicit_indexer.c
ffp/subwords/ngrams.cpython-36m-x86_64-linux-gnu.so
ffp/subwords/hash_indexers.c
ffp/subwords/explicit_indexer.pyx
ffp/storage/ndarray.py
ffp/storage/quantized.py
ffp/storage/__init__.py
ffp/storage/storage.py
